scatcluster/__init__.py
scatcluster/helper.py
scatcluster/scatcluster.py
scatcluster/structure.py
scatcluster/analysis/__init__.py
scatcluster/analysis/crosstab.py
scatcluster/analysis/dendrogram.py
scatcluster/analysis/external_correlation.py
scatcluster/analysis/predictions.py
scatcluster/analysis/processing.py
scatcluster/analysis/waveform_correlations.py
scatcluster/analysis/waveforms.py
scatcluster/processing/__init__.py
scatcluster/processing/ica.py
scatcluster/processing/scattering.py
scatcluster-0.0.87.dist-info/LICENSE
scatcluster-0.0.87.dist-info/METADATA
scatcluster-0.0.87.dist-info/WHEEL
scatcluster-0.0.87.dist-info/top_level.txt
scatcluster-0.0.87.dist-info/RECORD
